atap_context_extractor/ContextExtractor.py
atap_context_extractor/__init__.py
atap_context_extractor/extractor/ContextType.py
atap_context_extractor/extractor/Extractor.py
atap_context_extractor/extractor/SearchTerm.py
atap_context_extractor/extractor/__init__.py
atap_context_extractor-0.2.5.dist-info/LICENSE
atap_context_extractor-0.2.5.dist-info/METADATA
atap_context_extractor-0.2.5.dist-info/WHEEL
atap_context_extractor-0.2.5.dist-info/RECORD
